CHANGES.txt
CONTRIBUTORS.txt
README.txt
setup.cfg
setup.py
my/__init__.py
my.macro.concat.egg-info/PKG-INFO
my.macro.concat.egg-info/SOURCES.txt
my.macro.concat.egg-info/dependency_links.txt
my.macro.concat.egg-info/entry_points.txt
my.macro.concat.egg-info/namespace_packages.txt
my.macro.concat.egg-info/requires.txt
my.macro.concat.egg-info/top_level.txt
my.macro.concat.egg-info/zip-safe
my/macro/__init__.py
my/macro/concat/README.txt
my/macro/concat/__init__.py
my/macro/concat/tests/__init__.py
my/macro/concat/tests/test_docs.py