Metadata-Version: 1.0
Name: my.macro.concat
Version: 0.6.4dev
Summary: Concatenate an option on a target part from several other parts
Home-page: UNKNOWN
Author: Serge Renfer
Author-email: serge.renfer@gmail.com
License: ZPL
Keywords: buildout macro
Platform: UNKNOWN
Classifier: Framework :: Buildout
Classifier: Intended Audience :: Developers
Classifier: Topic :: Software Development :: Build Tools
Classifier: Topic :: Software Development :: Libraries :: Python Modules
Classifier: License :: OSI Approved :: Zope Public License
